{
	"info": {
		"_postman_id": "edb20108-532e-4fd5-a029-d41d6e4f0e69",
		"name": "ecommerce udacity",
		"schema": "https://schema.getpostman.com/json/collection/v2.1.0/collection.json",
		"_exporter_id": "18934015"
	},
	"item": [
		{
			"name": "create user",
			"request": {
				"method": "POST",
				"header": [],
				"body": {
					"mode": "raw",
					"raw": "{\r\n    \"username\": \"user\",\r\n    \"password\": \"somepassword\",\r\n    \"passwordConfirm\":\"somepassword\"\r\n}",
					"options": {
						"raw": {
							"language": "json"
						}
					}
				},
				"url": {
					"raw": "http://localhost:8080/api/user/create",
					"protocol": "http",
					"host": [
						"localhost"
					],
					"port": "8080",
					"path": [
						"api",
						"user",
						"create"
					]
				}
			},
			"response": []
		},
		{
			"name": "login",
			"request": {
				"method": "POST",
				"header": [],
				"body": {
					"mode": "raw",
					"raw": "{\r\n    \"username\": \"user\",\r\n    \"password\": \"somepassword\"\r\n}",
					"options": {
						"raw": {
							"language": "json"
						}
					}
				},
				"url": {
					"raw": "http://localhost:8080/login",
					"protocol": "http",
					"host": [
						"localhost"
					],
					"port": "8080",
					"path": [
						"login"
					]
				}
			},
			"response": []
		},
		{
			"name": "get user by id",
			"request": {
				"auth": {
					"type": "bearer",
					"bearer": [
						{
							"key": "token",
							"value": "eyJ0eXAiOiJKV1QiLCJhbGciOiJIUzUxMiJ9.eyJzdWIiOiJ1c2VyIiwiZXhwIjoxNjU3NzA0NDgzfQ.hALPEkAQFJzsgtjsIQRws1lKkmbNRJ30kOvHexyu4xex0nNfb85TrwNMs3oTnozZgl7WDGITglmwI6fGH2Dw7A",
							"type": "string"
						}
					]
				},
				"method": "GET",
				"header": [
					{
						"key": "Content-Type",
						"value": "application/json",
						"type": "text"
					}
				],
				"url": {
					"raw": "http://localhost:8080/api/user/id/1",
					"protocol": "http",
					"host": [
						"localhost"
					],
					"port": "8080",
					"path": [
						"api",
						"user",
						"id",
						"1"
					]
				}
			},
			"response": []
		},
		{
			"name": "get user by username",
			"request": {
				"auth": {
					"type": "bearer",
					"bearer": [
						{
							"key": "token",
							"value": "eyJ0eXAiOiJKV1QiLCJhbGciOiJIUzUxMiJ9.eyJzdWIiOiJ1c2VyIiwiZXhwIjoxNjU3NzA0NDgzfQ.hALPEkAQFJzsgtjsIQRws1lKkmbNRJ30kOvHexyu4xex0nNfb85TrwNMs3oTnozZgl7WDGITglmwI6fGH2Dw7A",
							"type": "string"
						}
					]
				},
				"method": "GET",
				"header": [],
				"url": {
					"raw": "http://localhost:8080/api/user/user",
					"protocol": "http",
					"host": [
						"localhost"
					],
					"port": "8080",
					"path": [
						"api",
						"user",
						"user"
					]
				}
			},
			"response": []
		},
		{
			"name": "get item by name",
			"request": {
				"auth": {
					"type": "bearer",
					"bearer": [
						{
							"key": "token",
							"value": "eyJ0eXAiOiJKV1QiLCJhbGciOiJIUzUxMiJ9.eyJzdWIiOiJ1c2VyIiwiZXhwIjoxNjU3NzA0NDgzfQ.hALPEkAQFJzsgtjsIQRws1lKkmbNRJ30kOvHexyu4xex0nNfb85TrwNMs3oTnozZgl7WDGITglmwI6fGH2Dw7A",
							"type": "string"
						}
					]
				},
				"method": "GET",
				"header": [],
				"url": {
					"raw": "http://localhost:8080/api/item/name/Widget",
					"protocol": "http",
					"host": [
						"localhost"
					],
					"port": "8080",
					"path": [
						"api",
						"item",
						"name",
						"Widget"
					]
				}
			},
			"response": []
		},
		{
			"name": "get items",
			"request": {
				"auth": {
					"type": "bearer",
					"bearer": [
						{
							"key": "token",
							"value": "eyJ0eXAiOiJKV1QiLCJhbGciOiJIUzUxMiJ9.eyJzdWIiOiJ1c2VyIiwiZXhwIjoxNjU3NzA0NDgzfQ.hALPEkAQFJzsgtjsIQRws1lKkmbNRJ30kOvHexyu4xex0nNfb85TrwNMs3oTnozZgl7WDGITglmwI6fGH2Dw7A",
							"type": "string"
						}
					]
				},
				"method": "GET",
				"header": [],
				"url": {
					"raw": "http://localhost:8080/api/item",
					"protocol": "http",
					"host": [
						"localhost"
					],
					"port": "8080",
					"path": [
						"api",
						"item"
					]
				}
			},
			"response": []
		},
		{
			"name": "add to cart",
			"request": {
				"auth": {
					"type": "bearer",
					"bearer": [
						{
							"key": "token",
							"value": "eyJ0eXAiOiJKV1QiLCJhbGciOiJIUzUxMiJ9.eyJzdWIiOiJ1c2VyIiwiZXhwIjoxNjU3NzA0NDgzfQ.hALPEkAQFJzsgtjsIQRws1lKkmbNRJ30kOvHexyu4xex0nNfb85TrwNMs3oTnozZgl7WDGITglmwI6fGH2Dw7A",
							"type": "string"
						}
					]
				},
				"method": "POST",
				"header": [],
				"body": {
					"mode": "raw",
					"raw": "{\r\n    \"username\": \"user\",\r\n    \"itemId\":1,\r\n    \"quantity\":2\r\n}",
					"options": {
						"raw": {
							"language": "json"
						}
					}
				},
				"url": {
					"raw": "http://localhost:8080/api/cart/addToCart",
					"protocol": "http",
					"host": [
						"localhost"
					],
					"port": "8080",
					"path": [
						"api",
						"cart",
						"addToCart"
					]
				}
			},
			"response": []
		},
		{
			"name": "removeFromCart",
			"request": {
				"auth": {
					"type": "bearer",
					"bearer": [
						{
							"key": "token",
							"value": "eyJ0eXAiOiJKV1QiLCJhbGciOiJIUzUxMiJ9.eyJzdWIiOiJ1c2VyIiwiZXhwIjoxNjU3NzA0NDgzfQ.hALPEkAQFJzsgtjsIQRws1lKkmbNRJ30kOvHexyu4xex0nNfb85TrwNMs3oTnozZgl7WDGITglmwI6fGH2Dw7A",
							"type": "string"
						}
					]
				},
				"method": "POST",
				"header": [],
				"body": {
					"mode": "raw",
					"raw": "{\r\n    \"username\":\"user\",\r\n    \"itemId\":2,\r\n    \"quantity\":1\r\n}",
					"options": {
						"raw": {
							"language": "json"
						}
					}
				},
				"url": {
					"raw": "http://localhost:8080/api/cart/removeFromCart",
					"protocol": "http",
					"host": [
						"localhost"
					],
					"port": "8080",
					"path": [
						"api",
						"cart",
						"removeFromCart"
					]
				}
			},
			"response": []
		},
		{
			"name": "submit order",
			"request": {
				"auth": {
					"type": "bearer",
					"bearer": [
						{
							"key": "token",
							"value": "eyJ0eXAiOiJKV1QiLCJhbGciOiJIUzUxMiJ9.eyJzdWIiOiJ1c2VyIiwiZXhwIjoxNjU3NzA0NDgzfQ.hALPEkAQFJzsgtjsIQRws1lKkmbNRJ30kOvHexyu4xex0nNfb85TrwNMs3oTnozZgl7WDGITglmwI6fGH2Dw7A",
							"type": "string"
						}
					]
				},
				"method": "POST",
				"header": [],
				"url": {
					"raw": "http://localhost:8080/api/order/submit/user",
					"protocol": "http",
					"host": [
						"localhost"
					],
					"port": "8080",
					"path": [
						"api",
						"order",
						"submit",
						"user"
					]
				}
			},
			"response": []
		},
		{
			"name": "history",
			"request": {
				"auth": {
					"type": "bearer",
					"bearer": [
						{
							"key": "token",
							"value": "eyJ0eXAiOiJKV1QiLCJhbGciOiJIUzUxMiJ9.eyJzdWIiOiJ1c2VyIiwiZXhwIjoxNjU3NzA0NDgzfQ.hALPEkAQFJzsgtjsIQRws1lKkmbNRJ30kOvHexyu4xex0nNfb85TrwNMs3oTnozZgl7WDGITglmwI6fGH2Dw7A",
							"type": "string"
						}
					]
				},
				"method": "GET",
				"header": [],
				"url": {
					"raw": "http://localhost:8080/api/order/history/user",
					"protocol": "http",
					"host": [
						"localhost"
					],
					"port": "8080",
					"path": [
						"api",
						"order",
						"history",
						"user"
					]
				}
			},
			"response": []
		}
	]
}